{
  "elections": [
    {
      "id": 1,
      "issue": "Best Kanye Album",
      "options": [
        "College Dropout",
        "Late Registration",
        "Graduation",
        "808s & Heartbreaks",
        "My Beautiful Dark Twisted Fantasy",
        "Yeezus",
        "The Life of Pablo",
        "Ye",
        "Jesus Is King",
        "Donda",
        "N/A"
      ]
    },
    {
      "id": 2,
      "issue": "Best Star Wars Movie",
      "options": [
        "Episode IV: A New Hope",
        "Episode V: The Empire Strikes Back",
        "Episode VI: Return of the Jedi",
        "Episode I: The Phantom Menace",
        "Episode II: Attack of the Clones",
        "Episode III: Revenge of the Sith",
        "Episode VII: The Force Awakens",
        "Episode VIII: The Last Jedi",
        "Episode IX: Rise of Skywalker",
        "Rogue One: A Star Wars Story",
        "Solo: A Star Wars Story",
        "N/A"
      ]
    },
    {
      "id": 3,
      "issue": "Best Bagel",
      "options": [
        "Everything",
        "Sesame",
        "Poppy",
        "Plain",
        "Garlic",
        "Onion",
        "Egg",
        "Cinnamon Raisin",
        "Salt",
        "N/A"
      ]
    },
    {
      "id": 4,
      "issue": "Best Fast Food",
      "options": [
        "McDonalds",
        "Wendy's",
        "Burger King",
        "Taco Bell",
        "KFC",
        "Chipotle",
        "Chick-Fil-A",
        "Subway",
        "Popeye's",
        "N/A"
      ]
    },
    {
      "id": 5,
      "issue": "Coolest Beatle",
      "options": [
        "John Lennon",
        "Paul McCartney",
        "George Harrison",
        "Ringo Starr",
        "N/A"
      ]
    },
    {
      "id": 6,
      "issue": "Coolest Member of the Fellowship of the Ring",
      "options": [
        "Frodo",
        "Sam",
        "Merry",
        "Pippin",
        "Gandalf",
        "Aragorn",
        "Legolas",
        "Gimli",
        "Boromir",
        "N/A"
      ]
    },
    {
      "id": 7,
      "issue": "Best Pizza Topping",
      "options": [
        "Pepperoni",
        "Sausage",
        "Onion",
        "Mushroom",
        "Pineapple",
        "Pepper",
        "Pickle",
        "Anchovy",
        "Olive",
        "N/A"
      ]
    },
    {
      "id": 8,
      "issue": "The NBA GOAT",
      "options": [
       "Michael Jordan",
       "LeBron James",
       "Kareem Abdul-Jabbar",
       "Magic Johnson",
       "Larry Bird",
       "Wilt Chamberlain",
       "Bill Russell",
       "Kobe Bryant",
       "Shaquille O'Neal",
       "Tim Duncan"
      ]
    },
    {
      "id": 9,
      "issue": "Best Season of The Wire",
      "options": [
        "Season 1",
        "Season 2",
        "Season 3",
        "Season 4",
        "Season 5"
      ]
    }
  ],
  "suggestions": [
    {
      "name": "Wes",
      "email": "wes.schierenbeck@gmail.com",
      "issue": "dummy submission",
      "options": [
        "Option1",
        "Option2",
        "Option3",
        "Option4",
        "Option5"
      ],
      "id": 1
    },
    {
      "name": "Wes Schierentest",
      "email": "wes.schierenbeck@gmail.com",
      "issue": "Coolest Color",
      "options": [
        "Red",
        "Blue",
        "Purple",
        "Orange",
        "Black",
        "White"
      ],
      "id": 2
    },
    {
      "name": "Wes",
      "email": "wes.schierenbeck@gmail.com",
      "issue": "Best Knicks",
      "options": [
        "Immanuel Quickley",
        "Derrick Rose",
        "Obi Toppin"
      ],
      "id": 3
    }
  ],
  "ballots1": [
    {
      "name": "Wes Schierenbeck",
      "email": "wschierenbeck@gmail.com",
      "votes": [
        "Graduation",
        "My Beautiful Dark Twisted Fantasy",
        "808s & Heartbreaks",
        "Yeezus",
        "College Dropout"
      ],
      "id": 1
    }
  ],
  "ballots2": [
    {
      "name": "Wes Schierenbeck",
      "email": "wschierenbeck@gmail.com",
      "votes": [
        "Episode VI: Return of the Jedi",
        "Episode V: The Empire Strikes Back",
        "Episode IV: A New Hope",
        "Episode I: The Phantom Menace",
        "Episode VII: The Force Awakens"
      ],
      "id": 1
    }
  ],
  "ballots3": [
    {
      "name": "Wes Schierenbeck",
      "email": "wschierenbeck@gmail.com",
      "votes": [
        "Everything",
        "Sesame",
        "Poppy",
        "Garlic",
        "Onion"
      ],
      "id": 1
    },
    {
      "name": "Tester",
      "email": "wes@wschierenbeck.com",
      "votes": [
        "Everything",
        "Sesame",
        "Poppy",
        "Garlic",
        "Onion"
      ],
      "id": 2
    }
  ],
  "ballots4": [
    {
      "name": "Wes Schierenbeck",
      "email": "wschierenbeck@gmail.com",
      "votes": [
        "McDonalds",
        "Popeye's",
        "Wendy's",
        "KFC",
        "Chick-Fil-A"
      ],
      "id": 1
    }
  ],
  "ballots5": [
    {
      "name": "Wes Schierenbeck",
      "email": "wschierenbeck@gmail.com",
      "votes": [
        "Paul McCartney",
        "George Harrison",
        "John Lennon",
        "Ringo Starr"
      ],
      "id": 1
    }
  ],
  "ballots6": [
    {
      "name": "Wes Schierenbeck",
      "email": "wschierenbeck@gmail.com",
      "votes": [
        "Gandalf",
        "Gimli",
        "Boromir",
        "Sam",
        "Frodo"
      ],
      "id": 1
    }
  ],
  "ballots7": [
    {
      "name": "Wes Schierenbeck",
      "email": "wschierenbeck@gmail.com",
      "votes": [
        "Mushroom",
        "Onion",
        "Pickle",
        "Pepper",
        "Olive"
      ],
      "id": 1
    }
  ],
  "ballots8": [
    {
      "name": "Wes Schierenbeck",
      "email": "wschierenbeck@gmail.com",
      "votes": [
        "Michael Jordan",
        "LeBron James",
        "Kareem Abdul-Jabbar",
        "Tim Duncan",
        "Wilt Chamberlain"
      ],
      "id": 1
    }
  ],
  "ballots9": [
    {
      "name": "Wes Schierenbeck",
      "email": "wschierenbeck@gmail.com",
      "votes": [
        "Season 4",
        "Season 2",
        "Season 3",
        "Season 1",
        "Season 5"
      ],
      "id": 1
    }
  ]
}